Workbook

Sheet Legal_Ethics
A1: RADS — Legal & Ethical Framework
A3: LEGAL NOTICE — READ BEFORE ACTING
A4: This tool provides decision SUPPORT only. It is not legal advice, and its output is not a decision to pay. A ransom payment must never be made on the basis of this workbook alone.
A5: 1. Sanctions exposure. Paying a ransom can be unlawful. Under EU restrictive measures and U.S. OFAC regulations, transferring value to a sanctioned person, group, or region may carry civil or criminal liability — in some regimes on a strict-liability basis, regardless of intent or knowledge. The identity of a ransomware operator is usually unknown at decision time, so this risk cannot be ruled out.
A6: 2. Reporting duties. In Germany, incidents may trigger notification to the BSI (BSIG / KRITIS obligations), to law enforcement (LKA/BKA), and — where personal data is affected — to the competent data-protection authority within 72 hours under GDPR Art. 33. Financial entities additionally fall under DORA (Reg. (EU) 2022/2554) major-incident reporting. Verify current obligations for your sector.
A7: 3. No guarantee. Payment does not guarantee a working decryptor, full data recovery, or that exfiltrated data will not be leaked or resold. It may also mark the organisation as a payer and invite repeat targeting.
A8: 4. Funding of criminal activity. A ransom payment directly finances criminal enterprises and the wider ransomware ecosystem, potentially enabling further attacks on this and other organisations. This is an ethical and, in some jurisdictions, a legal consideration that sits outside the economic calculation below.
A9: Before any payment: engage legal counsel, involve law enforcement, notify your cyber-insurer, and screen the counterparty against sanctions lists. Regulatory details may have changed since this template was written — confirm the current position.

Sheet Instructions
A1: How to use this workbook
A3: 1. Read the Legal_Ethics sheet first. It also reprints with every result.
A4: 2. Fill the yellow cells on Org_Info (organisation and incident parameters).
A5: 3. List every AFFECTED application on the Assets sheet, one per row. Fill the yellow columns only; the grey columns compute themselves.
A6: 4. Set Criticality from the dropdown (Critical / High / Medium / Low) and Backup Coverage as a percentage (share of that asset's data restorable from backup).
A7: 5. Open the Results sheet. It returns ONE organisation-level recommendation, driven by whether the Critical and High assets can be self-recovered. Low/Medium-criticality loss is treated as within tolerance.
A8: 6. The recommendation is decision SUPPORT, never authorisation. Follow the legal steps.
A10: Legend:
A11: Yellow = you fill in. Grey = computed, do not edit.

Sheet Org_Info
A1: Organisation & Incident Parameters
A2: Fill the yellow cells.
A4: Organisation Name | B4: Redport.DE (Redport Logistics GmbH)
A5: Assessment Date | B5: 2026-09-11
A6: Total Applications (org-wide) | B6: 240
A7: Current Ransom Demand (kEUR) | B7: 7500
A8: Ransom Doubling Period (days) | B8: 7
A9: Payment Deadline (days) | B9: 28
A10: Recovery Threshold (backup cov.) | B10: 0.5 | C10: Asset is 'self-recoverable' at or above this backup coverage
A11: P(decryptor works if paid) | B11: 0.65
A12: P(re-extortion after paying) | B12: 0.25
A13: Re-extortion Cost (kEUR) | B13: 3750
A14: P(data leaked even if paid) | B14: 0.35
A15: P(data leaked if NOT paid) | B15: 0.7
A16: Aggregate Leak Damage (kEUR) | B16: 6000
A17: Prior-incident handling | B17: Insufficient | C17: None / Insufficient / Sufficient (reference effect)
A18: Criticality weight — Critical | B18: 1 | C18: How heavily each tier's loss counts in the decision
A19: Criticality weight — High | B19: 0.75
A20: Criticality weight — Medium | B20: 0.5
A21: Criticality weight — Low | B21: 0.25

Sheet Assets
A1: Affected Applications / Assets
A2: Fill yellow columns (A–G). Grey columns (H–L) compute automatically.
A4: Application / Asset | B4: Criticality | C4: Affected? | D4: Backup Coverage | E4: Data Value (kEUR) | F4: Downtime Cost (kEUR/day) | G4: Self-Recovery Time (days) | H4: Crit. Weight | I4: Self-Recoverable? | J4: Exp. Recovery Loss (kEUR) | K4: Full Loss if Unrecovered (kEUR) | L4: Weighted No-Pay Loss (kEUR)
A5: Port Operations Control System (SCADA) | B5: Critical | C5: Yes | D5: 0.9 | E5: 3200 | F5: 220 | G5: 3 | H5: =IF($B5="Critical",Org_Info!$B$18,IF($B5="High",Org_Info!$B$19,IF($B5="Medium",Org_Info!$B$20,IF($B5="Low",Org_Info!$B$21,0)))) -> 1 | I5: =IF(AND($C5="Yes",$D5>=Org_Info!$B$10),"Yes","No") -> Yes | J5: =IF($C5="Yes",$F5*$G5+(1-$D5)*$E5,0) -> 980 | K5: =IF($C5="Yes",$E5+$F5*$G5,0) -> 3860 | L5: =IF($C5="Yes",$H5*IF($I5="Yes",$J5,$K5),0) -> 980
A6: Container Terminal Management System | B6: Critical | C6: Yes | D6: 0.85 | E6: 2800 | F6: 180 | G6: 4 | H6: =IF($B6="Critical",Org_Info!$B$18,IF($B6="High",Org_Info!$B$19,IF($B6="Medium",Org_Info!$B$20,IF($B6="Low",Org_Info!$B$21,0)))) -> 1 | I6: =IF(AND($C6="Yes",$D6>=Org_Info!$B$10),"Yes","No") -> Yes | J6: =IF($C6="Yes",$F6*$G6+(1-$D6)*$E6,0) -> 1140 | K6: =IF($C6="Yes",$E6+$F6*$G6,0) -> 3520 | L6: =IF($C6="Yes",$H6*IF($I6="Yes",$J6,$K6),0) -> 1140
A7: Customs Clearance Gateway (ATLAS) | B7: Critical | C7: Yes | D7: 0.2 | E7: 2600 | F7: 160 | G7: 12 | H7: =IF($B7="Critical",Org_Info!$B$18,IF($B7="High",Org_Info!$B$19,IF($B7="Medium",Org_Info!$B$20,IF($B7="Low",Org_Info!$B$21,0)))) -> 1 | I7: =IF(AND($C7="Yes",$D7>=Org_Info!$B$10),"Yes","No") -> No | J7: =IF($C7="Yes",$F7*$G7+(1-$D7)*$E7,0) -> 4000 | K7: =IF($C7="Yes",$E7+$F7*$G7,0) -> 4520 | L7: =IF($C7="Yes",$H7*IF($I7="Yes",$J7,$K7),0) -> 4520
A8: SAP S/4HANA (ERP core) | B8: Critical | C8: Yes | D8: 0.88 | E8: 4000 | F8: 200 | G8: 4 | H8: =IF($B8="Critical",Org_Info!$B$18,IF($B8="High",Org_Info!$B$19,IF($B8="Medium",Org_Info!$B$20,IF($B8="Low",Org_Info!$B$21,0)))) -> 1 | I8: =IF(AND($C8="Yes",$D8>=Org_Info!$B$10),"Yes","No") -> Yes | J8: =IF($C8="Yes",$F8*$G8+(1-$D8)*$E8,0) -> 1280 | K8: =IF($C8="Yes",$E8+$F8*$G8,0) -> 4800 | L8: =IF($C8="Yes",$H8*IF($I8="Yes",$J8,$K8),0) -> 1280
A9: Vessel Berth Scheduling | B9: Critical | C9: Yes | D9: 0.75 | E9: 1500 | F9: 140 | G9: 5 | H9: =IF($B9="Critical",Org_Info!$B$18,IF($B9="High",Org_Info!$B$19,IF($B9="Medium",Org_Info!$B$20,IF($B9="Low",Org_Info!$B$21,0)))) -> 1 | I9: =IF(AND($C9="Yes",$D9>=Org_Info!$B$10),"Yes","No") -> Yes | J9: =IF($C9="Yes",$F9*$G9+(1-$D9)*$E9,0) -> 1075 | K9: =IF($C9="Yes",$E9+$F9*$G9,0) -> 2200 | L9: =IF($C9="Yes",$H9*IF($I9="Yes",$J9,$K9),0) -> 1075
A10: Gate Automation & OCR | B10: Critical | C10: Yes | D10: 0.8 | E10: 900 | F10: 90 | G10: 4 | H10: =IF($B10="Critical",Org_Info!$B$18,IF($B10="High",Org_Info!$B$19,IF($B10="Medium",Org_Info!$B$20,IF($B10="Low",Org_Info!$B$21,0)))) -> 1 | I10: =IF(AND($C10="Yes",$D10>=Org_Info!$B$10),"Yes","No") -> Yes | J10: =IF($C10="Yes",$F10*$G10+(1-$D10)*$E10,0) -> 540 | K10: =IF($C10="Yes",$E10+$F10*$G10,0) -> 1260 | L10: =IF($C10="Yes",$H10*IF($I10="Yes",$J10,$K10),0) -> 540
A11: Yard Management System | B11: High | C11: Yes | D11: 0.8 | E11: 800 | F11: 70 | G11: 4 | H11: =IF($B11="Critical",Org_Info!$B$18,IF($B11="High",Org_Info!$B$19,IF($B11="Medium",Org_Info!$B$20,IF($B11="Low",Org_Info!$B$21,0)))) -> 0.75 | I11: =IF(AND($C11="Yes",$D11>=Org_Info!$B$10),"Yes","No") -> Yes | J11: =IF($C11="Yes",$F11*$G11+(1-$D11)*$E11,0) -> 440 | K11: =IF($C11="Yes",$E11+$F11*$G11,0) -> 1080 | L11: =IF($C11="Yes",$H11*IF($I11="Yes",$J11,$K11),0) -> 330
A12: Reefer (Cold-chain) Monitoring | B12: High | C12: Yes | D12: 0.78 | E12: 700 | F12: 90 | G12: 3 | H12: =IF($B12="Critical",Org_Info!$B$18,IF($B12="High",Org_Info!$B$19,IF($B12="Medium",Org_Info!$B$20,IF($B12="Low",Org_Info!$B$21,0)))) -> 0.75 | I12: =IF(AND($C12="Yes",$D12>=Org_Info!$B$10),"Yes","No") -> Yes | J12: =IF($C12="Yes",$F12*$G12+(1-$D12)*$E12,0) -> 424 | K12: =IF($C12="Yes",$E12+$F12*$G12,0) -> 970 | L12: =IF($C12="Yes",$H12*IF($I12="Yes",$J12,$K12),0) -> 318
A13: EDI Integration Hub | B13: High | C13: Yes | D13: 0.82 | E13: 600 | F13: 60 | G13: 4 | H13: =IF($B13="Critical",Org_Info!$B$18,IF($B13="High",Org_Info!$B$19,IF($B13="Medium",Org_Info!$B$20,IF($B13="Low",Org_Info!$B$21,0)))) -> 0.75 | I13: =IF(AND($C13="Yes",$D13>=Org_Info!$B$10),"Yes","No") -> Yes | J13: =IF($C13="Yes",$F13*$G13+(1-$D13)*$E13,0) -> 348 | K13: =IF($C13="Yes",$E13+$F13*$G13,0) -> 840 | L13: =IF($C13="Yes",$H13*IF($I13="Yes",$J13,$K13),0) -> 261
A14: Billing & Invoicing | B14: High | C14: Yes | D14: 0.85 | E14: 900 | F14: 50 | G14: 5 | H14: =IF($B14="Critical",Org_Info!$B$18,IF($B14="High",Org_Info!$B$19,IF($B14="Medium",Org_Info!$B$20,IF($B14="Low",Org_Info!$B$21,0)))) -> 0.75 | I14: =IF(AND($C14="Yes",$D14>=Org_Info!$B$10),"Yes","No") -> Yes | J14: =IF($C14="Yes",$F14*$G14+(1-$D14)*$E14,0) -> 385 | K14: =IF($C14="Yes",$E14+$F14*$G14,0) -> 1150 | L14: =IF($C14="Yes",$H14*IF($I14="Yes",$J14,$K14),0) -> 288.75
A15: Warehouse Management | B15: High | C15: Yes | D15: 0.76 | E15: 650 | F15: 55 | G15: 4 | H15: =IF($B15="Critical",Org_Info!$B$18,IF($B15="High",Org_Info!$B$19,IF($B15="Medium",Org_Info!$B$20,IF($B15="Low",Org_Info!$B$21,0)))) -> 0.75 | I15: =IF(AND($C15="Yes",$D15>=Org_Info!$B$10),"Yes","No") -> Yes | J15: =IF($C15="Yes",$F15*$G15+(1-$D15)*$E15,0) -> 376 | K15: =IF($C15="Yes",$E15+$F15*$G15,0) -> 870 | L15: =IF($C15="Yes",$H15*IF($I15="Yes",$J15,$K15),0) -> 282
A16: Fleet Telematics | B16: High | C16: Yes | D16: 0.7 | E16: 500 | F16: 45 | G16: 5 | H16: =IF($B16="Critical",Org_Info!$B$18,IF($B16="High",Org_Info!$B$19,IF($B16="Medium",Org_Info!$B$20,IF($B16="Low",Org_Info!$B$21,0)))) -> 0.75 | I16: =IF(AND($C16="Yes",$D16>=Org_Info!$B$10),"Yes","No") -> Yes | J16: =IF($C16="Yes",$F16*$G16+(1-$D16)*$E16,0) -> 375 | K16: =IF($C16="Yes",$E16+$F16*$G16,0) -> 725 | L16: =IF($C16="Yes",$H16*IF($I16="Yes",$J16,$K16),0) -> 281.25
... A56: Guest Wi-Fi Portal | B56: Low | C56: Yes | D56: 0.65 | E56: 35 | F56: 3 | G56: 2 | H56: =IF($B56="Critical",Org_Info!$B$18,IF($B56="High",Org_Info!$B$19,IF($B56="Medium",Org_Info!$B$20,IF($B56="Low",Org_Info!$B$21,0)))) -> 0.25 | I56: =IF(AND($C56="Yes",$D56>=Org_Info!$B$10),"Yes","No") -> Yes | J56: =IF($C56="Yes",$F56*$G56+(1-$D56)*$E56,0) -> 18.25 | K56: =IF($C56="Yes",$E56+$F56*$G56,0) -> 41 | L56: =IF($C56="Yes",$H56*IF($I56="Yes",$J56,$K56),0) -> 4.5625

Sheet Results
A1: RADS — Organisation-Level Recommendation
A2: DECISION SUPPORT ONLY — NOT LEGAL ADVICE AND NOT AUTHORISATION TO PAY. A payment can breach EU/OFAC sanctions and funds criminal activity. See the Legal_Ethics sheet and involve counsel + law enforcement before acting.
A5: Portfolio summary
A6: Affected — Critical | C6: =COUNTIFS(Assets!$C$5:$C$56,"Yes",Assets!$B$5:$B$56,"Critical") -> 6
A7: Affected — High | C7: =COUNTIFS(Assets!$C$5:$C$56,"Yes",Assets!$B$5:$B$56,"High") -> 10
A8: Affected — Medium | C8: =COUNTIFS(Assets!$C$5:$C$56,"Yes",Assets!$B$5:$B$56,"Medium") -> 12
A9: Affected — Low | C9: =COUNTIFS(Assets!$C$5:$C$56,"Yes",Assets!$B$5:$B$56,"Low") -> 24
A10: Criticality-weighted stranded exposure (kEUR) | C10: =SUMIFS(Assets!$L$5:$L$56,Assets!$I$5:$I$56,"No",Assets!$C$5:$C$56,"Yes") -> 4520 | E10: unrecoverable loss, each asset scaled by its criticality weight (all tiers count)
A12: Economic comparison — criticality-weighted (expected, kEUR)
A13: Weighted cost if NOT paying | C13: =SUM(Assets!$L$5:$L$56) -> 13129
A14: Weighted cost if paying | C14: =Org_Info!$B$7+(1-Org_Info!$B$11)*(SUM(Assets!$L$5:$L$56))+Org_Info!$B$12*Org_Info!$B$13+Org_Info!$B$14*Org_Info!$B$16 -> 15132.65
A15: Weighted saving from paying | C15: =$C$13-$C$14 -> -2003.65 | E15: positive = paying is cheaper once losses are criticality-weighted (before legal/ethical factors)
A17: RECOMMENDATION
A18: =IF($C$15>0,"CONSIDER PAYMENT — subject to mandatory legal & sanctions review","DO NOT PAY — self-recovery is cheaper on a criticality-weighted basis") -> DO NOT PAY — self-recovery is cheaper on a criticality-weighted basis
A21: ="Decision is driven by a criticality-weighted comparison: each asset's loss counts in "&"proportion to its weight (Critical..Low), so high-value systems dominate and "&"low/medium losses count but do not swamp the result. Weighted stranded exposure = "&TEXT($C$10,"#,##0")&" kEUR." -> Decision is driven by a criticality-weighted comparison: each asset's loss counts in proportion to its weight (Critical..Low), so high-value systems dominate and low/medium losses count but do not swamp the result. Weighted stranded exposure = 4,520 kEUR.
A24: Reminder: a 'CONSIDER PAYMENT' result is an economic signal only. It does not resolve sanctions, reporting, or the ethical cost of funding crime — resolve those before any payment.
